amundsen_rds/__init__.py
amundsen_rds/alembic.ini
amundsen_rds/py.typed
amundsen_rds/migrations/__init__.py
amundsen_rds/migrations/env.py
amundsen_rds/migrations/versions/__init__.py
amundsen_rds/migrations/versions/a539c998cc1e_add_profile_url_column_to_users_table.py
amundsen_rds/migrations/versions/aa30b4276b9b_add_table_column_lineage.py
amundsen_rds/migrations/versions/c194a2dc1240_initial_commit.py
amundsen_rds/models/__init__.py
amundsen_rds/models/application.py
amundsen_rds/models/badge.py
amundsen_rds/models/base.py
amundsen_rds/models/cluster.py
amundsen_rds/models/column.py
amundsen_rds/models/dashboard.py
amundsen_rds/models/database.py
amundsen_rds/models/schema.py
amundsen_rds/models/table.py
amundsen_rds/models/tag.py
amundsen_rds/models/updated_timestamp.py
amundsen_rds/models/user.py
amundsen_rds-0.0.8.dist-info/LICENSE
amundsen_rds-0.0.8.dist-info/METADATA
amundsen_rds-0.0.8.dist-info/WHEEL
amundsen_rds-0.0.8.dist-info/top_level.txt
amundsen_rds-0.0.8.dist-info/RECORD
