Metadata-Version: 2.1
Name: amundsen-rds
Version: 0.0.8
Summary: Amundsen ORM Support
Home-page: https://www.github.com/amundsen-io/amundsenrds
Maintainer: Amundsen TSC
Maintainer-email: amundsen-tsc@lists.lfai.foundation
License: UNKNOWN
Platform: UNKNOWN
Classifier: Programming Language :: Python :: 3.6
Classifier: Programming Language :: Python :: 3.7
Requires-Python: >=3.6
Requires-Dist: sqlalchemy (>=1.3.0)
Requires-Dist: alembic (<2.0,>=1.2)
